[
    {
        "ID": 62151,
        "UserID": "auth0|60c4ddb2612d820070a5e2f6",
        "IdentityID": 25895,
        "CreatedAt": "2022-09-25 05:23:56",
        "Flags": 0,
        "VerdictType": 0,
        "VerdictResult": 0,
        "VerdictName": "Valid",
        "VerdictValue": "Valid",
        "VIP": 0,
        "Ban": 0
    },
    {
        "ID": 62150,
        "UserID": "auth0|60c4ddb2612d820070a5e2f6",
        "IdentityID": 45020,
        "CreatedAt": "2022-09-25 05:23:49",
        "Flags": 0,
        "VerdictType": 0,
        "VerdictResult": 0,
        "VerdictName": "Valid",
        "VerdictValue": "Valid",
        "VIP": 0,
        "Ban": 0
    },
    {
        "ID": 62149,
        "UserID": "auth0|60c4ddb2612d820070a5e2f6",
        "IdentityID": 4769,
        "CreatedAt": "2022-09-25 05:23:28",
        "Flags": 0,
        "VerdictType": 0,
        "VerdictResult": 0,
        "VerdictName": "Valid",
        "VerdictValue": "Valid",
        "VIP": 0,
        "Ban": 0
    },
    {
        "ID": 62148,
        "UserID": "auth0|60c4ddb2612d820070a5e2f6",
        "IdentityID": 36099,
        "CreatedAt": "2022-09-25 05:22:25",
        "Flags": 0,
        "VerdictType": 0,
        "VerdictResult": 0,
        "VerdictName": "Valid",
        "VerdictValue": "Valid",
        "VIP": 0,
        "Ban": 0
    },
    {
        "ID": 62147,
        "UserID": "auth0|60c4ddb2612d820070a5e2f6",
        "IdentityID": 29129,
        "CreatedAt": "2022-09-25 05:22:12",
        "Flags": 0,
        "VerdictType": 0,
        "VerdictResult": 0,
        "VerdictName": "Valid",
        "VerdictValue": "Valid",
        "VIP": 0,
        "Ban": 0
    },
    {
        "ID": 62146,
        "UserID": "auth0|60c4ddb2612d820070a5e2f6",
        "IdentityID": 45019,
        "CreatedAt": "2022-09-25 05:18:21",
        "Flags": 0,
        "VerdictType": 0,
        "VerdictResult": 0,
        "VerdictName": "Valid",
        "VerdictValue": "Valid",
        "VIP": 0,
        "Ban": 0
    },
    {
        "ID": 62145,
        "UserID": "auth0|60c4ddb2612d820070a5e2f6",
        "IdentityID": 45018,
        "CreatedAt": "2022-09-25 05:17:59",
        "Flags": 0,
        "VerdictType": 0,
        "VerdictResult": 0,
        "VerdictName": "Valid",
        "VerdictValue": "Valid",
        "VIP": 0,
        "Ban": 0
    },
    {
        "ID": 62144,
        "UserID": "auth0|60c4ddb2612d820070a5e2f6",
        "IdentityID": 45017,
        "CreatedAt": "2022-09-25 05:17:48",
        "Flags": 0,
        "VerdictType": 0,
        "VerdictResult": 0,
        "VerdictName": "Valid",
        "VerdictValue": "Valid",
        "VIP": 0,
        "Ban": 0
    },
    {
        "ID": 62143,
        "UserID": "auth0|60c4ddb2612d820070a5e2f6",
        "IdentityID": 45016,
        "CreatedAt": "2022-09-25 05:17:41",
        "Flags": 0,
        "VerdictType": 0,
        "VerdictResult": 0,
        "VerdictName": "Valid",
        "VerdictValue": "Valid",
        "VIP": 0,
        "Ban": 0
    },
    {
        "ID": 62142,
        "UserID": "auth0|60c4ddb2612d820070a5e2f6",
        "IdentityID": 45015,
        "CreatedAt": "2022-09-25 05:17:28",
        "Flags": 0,
        "VerdictType": 0,
        "VerdictResult": 0,
        "VerdictName": "Valid",
        "VerdictValue": "Valid",
        "VIP": 0,
        "Ban": 0
    },
    {
        "ID": 62141,
        "UserID": "auth0|60c4ddb2612d820070a5e2f6",
        "IdentityID": 45014,
        "CreatedAt": "2022-09-25 05:17:16",
        "Flags": 0,
        "VerdictType": 0,
        "VerdictResult": 0,
        "VerdictName": "Valid",
        "VerdictValue": "Valid",
        "VIP": 0,
        "Ban": 0
    },
    {
        "ID": 62140,
        "UserID": "auth0|60c4ddb2612d820070a5e2f6",
        "IdentityID": 44325,
        "CreatedAt": "2022-09-25 05:16:17",
        "Flags": 0,
        "VerdictType": 0,
        "VerdictResult": 0,
        "VerdictName": "Valid",
        "VerdictValue": "Valid",
        "VIP": 0,
        "Ban": 0
    },
    {
        "ID": 62139,
        "UserID": "auth0|60c4ddb2612d820070a5e2f6",
        "IdentityID": 45013,
        "CreatedAt": "2022-09-25 05:15:17",
        "Flags": 0,
        "VerdictType": 0,
        "VerdictResult": 0,
        "VerdictName": "Valid",
        "VerdictValue": "Valid",
        "VIP": 0,
        "Ban": 0
    },
    {
        "ID": 62138,
        "UserID": "auth0|60c4ddb2612d820070a5e2f6",
        "IdentityID": 45012,
        "CreatedAt": "2022-09-25 05:15:09",
        "Flags": 0,
        "VerdictType": 0,
        "VerdictResult": 0,
        "VerdictName": "Valid",
        "VerdictValue": "Valid",
        "VIP": 0,
        "Ban": 0
    },
    {
        "ID": 62137,
        "UserID": "auth0|60c4ddb2612d820070a5e2f6",
        "IdentityID": 45011,
        "CreatedAt": "2022-09-25 05:15:01",
        "Flags": 0,
        "VerdictType": 0,
        "VerdictResult": 0,
        "VerdictName": "Valid",
        "VerdictValue": "Valid",
        "VIP": 0,
        "Ban": 0
    },
    {
        "ID": 62136,
        "UserID": "auth0|60c4ddb2612d820070a5e2f6",
        "IdentityID": 45010,
        "CreatedAt": "2022-09-25 05:14:53",
        "Flags": 0,
        "VerdictType": 0,
        "VerdictResult": 0,
        "VerdictName": "Valid",
        "VerdictValue": "Valid",
        "VIP": 0,
        "Ban": 0
    },
    {
        "ID": 62135,
        "UserID": "auth0|60c4ddb2612d820070a5e2f6",
        "IdentityID": 45009,
        "CreatedAt": "2022-09-25 05:14:45",
        "Flags": 0,
        "VerdictType": 0,
        "VerdictResult": 0,
        "VerdictName": "Valid",
        "VerdictValue": "Valid",
        "VIP": 0,
        "Ban": 0
    },
    {
        "ID": 62134,
        "UserID": "auth0|60c4ddb2612d820070a5e2f6",
        "IdentityID": 45008,
        "CreatedAt": "2022-09-25 05:14:36",
        "Flags": 0,
        "VerdictType": 0,
        "VerdictResult": 0,
        "VerdictName": "Valid",
        "VerdictValue": "Valid",
        "VIP": 0,
        "Ban": 0
    },
    {
        "ID": 62133,
        "UserID": "auth0|60c4ddb2612d820070a5e2f6",
        "IdentityID": 9361,
        "CreatedAt": "2022-09-25 05:14:28",
        "Flags": 0,
        "VerdictType": 0,
        "VerdictResult": 0,
        "VerdictName": "Valid",
        "VerdictValue": "Valid",
        "VIP": 0,
        "Ban": 0
    },
    {
        "ID": 62132,
        "UserID": "auth0|60c4ddb2612d820070a5e2f6",
        "IdentityID": 42371,
        "CreatedAt": "2022-09-25 05:14:19",
        "Flags": 0,
        "VerdictType": 0,
        "VerdictResult": 0,
        "VerdictName": "Valid",
        "VerdictValue": "Valid",
        "VIP": 0,
        "Ban": 0
    },
    {
        "ID": 62131,
        "UserID": "auth0|60c4ddb2612d820070a5e2f6",
        "IdentityID": 45007,
        "CreatedAt": "2022-09-25 05:14:07",
        "Flags": 0,
        "VerdictType": 0,
        "VerdictResult": 0,
        "VerdictName": "Valid",
        "VerdictValue": "Valid",
        "VIP": 0,
        "Ban": 0
    },
    {
        "ID": 62130,
        "UserID": "auth0|60c4ddb2612d820070a5e2f6",
        "IdentityID": 45006,
        "CreatedAt": "2022-09-25 05:13:58",
        "Flags": 0,
        "VerdictType": 0,
        "VerdictResult": 0,
        "VerdictName": "Valid",
        "VerdictValue": "Valid",
        "VIP": 0,
        "Ban": 0
    },
    {
        "ID": 62129,
        "UserID": "auth0|60c4ddb2612d820070a5e2f6",
        "IdentityID": 45005,
        "CreatedAt": "2022-09-25 05:13:52",
        "Flags": 0,
        "VerdictType": 0,
        "VerdictResult": 0,
        "VerdictName": "Valid",
        "VerdictValue": "Valid",
        "VIP": 0,
        "Ban": 0
    },
    {
        "ID": 62128,
        "UserID": "auth0|60c4ddb2612d820070a5e2f6",
        "IdentityID": 45004,
        "CreatedAt": "2022-09-25 05:13:38",
        "Flags": 0,
        "VerdictType": 0,
        "VerdictResult": 0,
        "VerdictName": "Valid",
        "VerdictValue": "Valid",
        "VIP": 0,
        "Ban": 0
    },
    {
        "ID": 62127,
        "UserID": "auth0|60c4ddb2612d820070a5e2f6",
        "IdentityID": 45003,
        "CreatedAt": "2022-09-25 05:13:29",
        "Flags": 0,
        "VerdictType": 0,
        "VerdictResult": 0,
        "VerdictName": "Valid",
        "VerdictValue": "Valid",
        "VIP": 0,
        "Ban": 0
    },
    {
        "ID": 62151,
        "UserID": "auth0|60c4ddb2612d820070a5e2f6",
        "IdentityID": 25895,
        "CreatedAt": "2022-09-25 05:23:56",
        "Flags": 0,
        "VerdictType": 0,
        "VerdictResult": 0,
        "VerdictName": "Valid",
        "VerdictValue": "Valid",
        "VIP": 0,
        "Ban": 0
    },
    {
        "ID": 62150,
        "UserID": "auth0|60c4ddb2612d820070a5e2f6",
        "IdentityID": 45020,
        "CreatedAt": "2022-09-25 05:23:49",
        "Flags": 0,
        "VerdictType": 0,
        "VerdictResult": 0,
        "VerdictName": "Valid",
        "VerdictValue": "Valid",
        "VIP": 0,
        "Ban": 0
    },
    {
        "ID": 62149,
        "UserID": "auth0|60c4ddb2612d820070a5e2f6",
        "IdentityID": 4769,
        "CreatedAt": "2022-09-25 05:23:28",
        "Flags": 0,
        "VerdictType": 0,
        "VerdictResult": 0,
        "VerdictName": "Valid",
        "VerdictValue": "Valid",
        "VIP": 0,
        "Ban": 0
    },
    {
        "ID": 62148,
        "UserID": "auth0|60c4ddb2612d820070a5e2f6",
        "IdentityID": 36099,
        "CreatedAt": "2022-09-25 05:22:25",
        "Flags": 0,
        "VerdictType": 0,
        "VerdictResult": 0,
        "VerdictName": "Valid",
        "VerdictValue": "Valid",
        "VIP": 0,
        "Ban": 0
    },
    {
        "ID": 62147,
        "UserID": "auth0|60c4ddb2612d820070a5e2f6",
        "IdentityID": 29129,
        "CreatedAt": "2022-09-25 05:22:12",
        "Flags": 0,
        "VerdictType": 0,
        "VerdictResult": 0,
        "VerdictName": "Valid",
        "VerdictValue": "Valid",
        "VIP": 0,
        "Ban": 0
    },
    {
        "ID": 62146,
        "UserID": "auth0|60c4ddb2612d820070a5e2f6",
        "IdentityID": 45019,
        "CreatedAt": "2022-09-25 05:18:21",
        "Flags": 0,
        "VerdictType": 0,
        "VerdictResult": 0,
        "VerdictName": "Valid",
        "VerdictValue": "Valid",
        "VIP": 0,
        "Ban": 0
    },
    {
        "ID": 62145,
        "UserID": "auth0|60c4ddb2612d820070a5e2f6",
        "IdentityID": 45018,
        "CreatedAt": "2022-09-25 05:17:59",
        "Flags": 0,
        "VerdictType": 0,
        "VerdictResult": 0,
        "VerdictName": "Valid",
        "VerdictValue": "Valid",
        "VIP": 0,
        "Ban": 0
    },
    {
        "ID": 62144,
        "UserID": "auth0|60c4ddb2612d820070a5e2f6",
        "IdentityID": 45017,
        "CreatedAt": "2022-09-25 05:17:48",
        "Flags": 0,
        "VerdictType": 0,
        "VerdictResult": 0,
        "VerdictName": "Valid",
        "VerdictValue": "Valid",
        "VIP": 0,
        "Ban": 0
    },
    {
        "ID": 62143,
        "UserID": "auth0|60c4ddb2612d820070a5e2f6",
        "IdentityID": 45016,
        "CreatedAt": "2022-09-25 05:17:41",
        "Flags": 0,
        "VerdictType": 0,
        "VerdictResult": 0,
        "VerdictName": "Valid",
        "VerdictValue": "Valid",
        "VIP": 0,
        "Ban": 0
    },
    {
        "ID": 62142,
        "UserID": "auth0|60c4ddb2612d820070a5e2f6",
        "IdentityID": 45015,
        "CreatedAt": "2022-09-25 05:17:28",
        "Flags": 0,
        "VerdictType": 0,
        "VerdictResult": 0,
        "VerdictName": "Valid",
        "VerdictValue": "Valid",
        "VIP": 0,
        "Ban": 0
    },
    {
        "ID": 62141,
        "UserID": "auth0|60c4ddb2612d820070a5e2f6",
        "IdentityID": 45014,
        "CreatedAt": "2022-09-25 05:17:16",
        "Flags": 0,
        "VerdictType": 0,
        "VerdictResult": 0,
        "VerdictName": "Valid",
        "VerdictValue": "Valid",
        "VIP": 0,
        "Ban": 0
    },
    {
        "ID": 62140,
        "UserID": "auth0|60c4ddb2612d820070a5e2f6",
        "IdentityID": 44325,
        "CreatedAt": "2022-09-25 05:16:17",
        "Flags": 0,
        "VerdictType": 0,
        "VerdictResult": 0,
        "VerdictName": "Valid",
        "VerdictValue": "Valid",
        "VIP": 0,
        "Ban": 0
    },
    {
        "ID": 62139,
        "UserID": "auth0|60c4ddb2612d820070a5e2f6",
        "IdentityID": 45013,
        "CreatedAt": "2022-09-25 05:15:17",
        "Flags": 0,
        "VerdictType": 0,
        "VerdictResult": 0,
        "VerdictName": "Valid",
        "VerdictValue": "Valid",
        "VIP": 0,
        "Ban": 0
    },
    {
        "ID": 62138,
        "UserID": "auth0|60c4ddb2612d820070a5e2f6",
        "IdentityID": 45012,
        "CreatedAt": "2022-09-25 05:15:09",
        "Flags": 0,
        "VerdictType": 0,
        "VerdictResult": 0,
        "VerdictName": "Valid",
        "VerdictValue": "Valid",
        "VIP": 0,
        "Ban": 0
    },
    {
        "ID": 62137,
        "UserID": "auth0|60c4ddb2612d820070a5e2f6",
        "IdentityID": 45011,
        "CreatedAt": "2022-09-25 05:15:01",
        "Flags": 0,
        "VerdictType": 0,
        "VerdictResult": 0,
        "VerdictName": "Valid",
        "VerdictValue": "Valid",
        "VIP": 0,
        "Ban": 0
    },
    {
        "ID": 62136,
        "UserID": "auth0|60c4ddb2612d820070a5e2f6",
        "IdentityID": 45010,
        "CreatedAt": "2022-09-25 05:14:53",
        "Flags": 0,
        "VerdictType": 0,
        "VerdictResult": 0,
        "VerdictName": "Valid",
        "VerdictValue": "Valid",
        "VIP": 0,
        "Ban": 0
    },
    {
        "ID": 62135,
        "UserID": "auth0|60c4ddb2612d820070a5e2f6",
        "IdentityID": 45009,
        "CreatedAt": "2022-09-25 05:14:45",
        "Flags": 0,
        "VerdictType": 0,
        "VerdictResult": 0,
        "VerdictName": "Valid",
        "VerdictValue": "Valid",
        "VIP": 0,
        "Ban": 0
    },
    {
        "ID": 62134,
        "UserID": "auth0|60c4ddb2612d820070a5e2f6",
        "IdentityID": 45008,
        "CreatedAt": "2022-09-25 05:14:36",
        "Flags": 0,
        "VerdictType": 0,
        "VerdictResult": 0,
        "VerdictName": "Valid",
        "VerdictValue": "Valid",
        "VIP": 0,
        "Ban": 0
    },
    {
        "ID": 62133,
        "UserID": "auth0|60c4ddb2612d820070a5e2f6",
        "IdentityID": 9361,
        "CreatedAt": "2022-09-25 05:14:28",
        "Flags": 0,
        "VerdictType": 0,
        "VerdictResult": 0,
        "VerdictName": "Valid",
        "VerdictValue": "Valid",
        "VIP": 0,
        "Ban": 0
    },
    {
        "ID": 62132,
        "UserID": "auth0|60c4ddb2612d820070a5e2f6",
        "IdentityID": 42371,
        "CreatedAt": "2022-09-25 05:14:19",
        "Flags": 0,
        "VerdictType": 0,
        "VerdictResult": 0,
        "VerdictName": "Valid",
        "VerdictValue": "Valid",
        "VIP": 0,
        "Ban": 0
    },
    {
        "ID": 62131,
        "UserID": "auth0|60c4ddb2612d820070a5e2f6",
        "IdentityID": 45007,
        "CreatedAt": "2022-09-25 05:14:07",
        "Flags": 0,
        "VerdictType": 0,
        "VerdictResult": 0,
        "VerdictName": "Valid",
        "VerdictValue": "Valid",
        "VIP": 0,
        "Ban": 0
    },
    {
        "ID": 62130,
        "UserID": "auth0|60c4ddb2612d820070a5e2f6",
        "IdentityID": 45006,
        "CreatedAt": "2022-09-25 05:13:58",
        "Flags": 0,
        "VerdictType": 0,
        "VerdictResult": 0,
        "VerdictName": "Valid",
        "VerdictValue": "Valid",
        "VIP": 0,
        "Ban": 0
    },
    {
        "ID": 62129,
        "UserID": "auth0|60c4ddb2612d820070a5e2f6",
        "IdentityID": 45005,
        "CreatedAt": "2022-09-25 05:13:52",
        "Flags": 0,
        "VerdictType": 0,
        "VerdictResult": 0,
        "VerdictName": "Valid",
        "VerdictValue": "Valid",
        "VIP": 0,
        "Ban": 0
    },
    {
        "ID": 62128,
        "UserID": "auth0|60c4ddb2612d820070a5e2f6",
        "IdentityID": 45004,
        "CreatedAt": "2022-09-25 05:13:38",
        "Flags": 0,
        "VerdictType": 0,
        "VerdictResult": 0,
        "VerdictName": "Valid",
        "VerdictValue": "Valid",
        "VIP": 0,
        "Ban": 0
    },
    {
        "ID": 62127,
        "UserID": "auth0|60c4ddb2612d820070a5e2f6",
        "IdentityID": 45003,
        "CreatedAt": "2022-09-25 05:13:29",
        "Flags": 0,
        "VerdictType": 0,
        "VerdictResult": 0,
        "VerdictName": "Valid",
        "VerdictValue": "Valid",
        "VIP": 0,
        "Ban": 0
    },
    {
        "ID": 62151,
        "UserID": "auth0|60c4ddb2612d820070a5e2f6",
        "IdentityID": 25895,
        "CreatedAt": "2022-09-25 05:23:56",
        "Flags": 0,
        "VerdictType": 0,
        "VerdictResult": 0,
        "VerdictName": "Valid",
        "VerdictValue": "Valid",
        "VIP": 0,
        "Ban": 0
    },
    {
        "ID": 62150,
        "UserID": "auth0|60c4ddb2612d820070a5e2f6",
        "IdentityID": 45020,
        "CreatedAt": "2022-09-25 05:23:49",
        "Flags": 0,
        "VerdictType": 0,
        "VerdictResult": 0,
        "VerdictName": "Valid",
        "VerdictValue": "Valid",
        "VIP": 0,
        "Ban": 0
    },
    {
        "ID": 62149,
        "UserID": "auth0|60c4ddb2612d820070a5e2f6",
        "IdentityID": 4769,
        "CreatedAt": "2022-09-25 05:23:28",
        "Flags": 0,
        "VerdictType": 0,
        "VerdictResult": 0,
        "VerdictName": "Valid",
        "VerdictValue": "Valid",
        "VIP": 0,
        "Ban": 0
    },
    {
        "ID": 62148,
        "UserID": "auth0|60c4ddb2612d820070a5e2f6",
        "IdentityID": 36099,
        "CreatedAt": "2022-09-25 05:22:25",
        "Flags": 0,
        "VerdictType": 0,
        "VerdictResult": 0,
        "VerdictName": "Valid",
        "VerdictValue": "Valid",
        "VIP": 0,
        "Ban": 0
    },
    {
        "ID": 62147,
        "UserID": "auth0|60c4ddb2612d820070a5e2f6",
        "IdentityID": 29129,
        "CreatedAt": "2022-09-25 05:22:12",
        "Flags": 0,
        "VerdictType": 0,
        "VerdictResult": 0,
        "VerdictName": "Valid",
        "VerdictValue": "Valid",
        "VIP": 0,
        "Ban": 0
    },
    {
        "ID": 62146,
        "UserID": "auth0|60c4ddb2612d820070a5e2f6",
        "IdentityID": 45019,
        "CreatedAt": "2022-09-25 05:18:21",
        "Flags": 0,
        "VerdictType": 0,
        "VerdictResult": 0,
        "VerdictName": "Valid",
        "VerdictValue": "Valid",
        "VIP": 0,
        "Ban": 0
    },
    {
        "ID": 62145,
        "UserID": "auth0|60c4ddb2612d820070a5e2f6",
        "IdentityID": 45018,
        "CreatedAt": "2022-09-25 05:17:59",
        "Flags": 0,
        "VerdictType": 0,
        "VerdictResult": 0,
        "VerdictName": "Valid",
        "VerdictValue": "Valid",
        "VIP": 0,
        "Ban": 0
    },
    {
        "ID": 62144,
        "UserID": "auth0|60c4ddb2612d820070a5e2f6",
        "IdentityID": 45017,
        "CreatedAt": "2022-09-25 05:17:48",
        "Flags": 0,
        "VerdictType": 0,
        "VerdictResult": 0,
        "VerdictName": "Valid",
        "VerdictValue": "Valid",
        "VIP": 0,
        "Ban": 0
    },
    {
        "ID": 62143,
        "UserID": "auth0|60c4ddb2612d820070a5e2f6",
        "IdentityID": 45016,
        "CreatedAt": "2022-09-25 05:17:41",
        "Flags": 0,
        "VerdictType": 0,
        "VerdictResult": 0,
        "VerdictName": "Valid",
        "VerdictValue": "Valid",
        "VIP": 0,
        "Ban": 0
    },
    {
        "ID": 62142,
        "UserID": "auth0|60c4ddb2612d820070a5e2f6",
        "IdentityID": 45015,
        "CreatedAt": "2022-09-25 05:17:28",
        "Flags": 0,
        "VerdictType": 0,
        "VerdictResult": 0,
        "VerdictName": "Valid",
        "VerdictValue": "Valid",
        "VIP": 0,
        "Ban": 0
    },
    {
        "ID": 62141,
        "UserID": "auth0|60c4ddb2612d820070a5e2f6",
        "IdentityID": 45014,
        "CreatedAt": "2022-09-25 05:17:16",
        "Flags": 0,
        "VerdictType": 0,
        "VerdictResult": 0,
        "VerdictName": "Valid",
        "VerdictValue": "Valid",
        "VIP": 0,
        "Ban": 0
    },
    {
        "ID": 62140,
        "UserID": "auth0|60c4ddb2612d820070a5e2f6",
        "IdentityID": 44325,
        "CreatedAt": "2022-09-25 05:16:17",
        "Flags": 0,
        "VerdictType": 0,
        "VerdictResult": 0,
        "VerdictName": "Valid",
        "VerdictValue": "Valid",
        "VIP": 0,
        "Ban": 0
    },
    {
        "ID": 62139,
        "UserID": "auth0|60c4ddb2612d820070a5e2f6",
        "IdentityID": 45013,
        "CreatedAt": "2022-09-25 05:15:17",
        "Flags": 0,
        "VerdictType": 0,
        "VerdictResult": 0,
        "VerdictName": "Valid",
        "VerdictValue": "Valid",
        "VIP": 0,
        "Ban": 0
    },
    {
        "ID": 62138,
        "UserID": "auth0|60c4ddb2612d820070a5e2f6",
        "IdentityID": 45012,
        "CreatedAt": "2022-09-25 05:15:09",
        "Flags": 0,
        "VerdictType": 0,
        "VerdictResult": 0,
        "VerdictName": "Valid",
        "VerdictValue": "Valid",
        "VIP": 0,
        "Ban": 0
    },
    {
        "ID": 62137,
        "UserID": "auth0|60c4ddb2612d820070a5e2f6",
        "IdentityID": 45011,
        "CreatedAt": "2022-09-25 05:15:01",
        "Flags": 0,
        "VerdictType": 0,
        "VerdictResult": 0,
        "VerdictName": "Valid",
        "VerdictValue": "Valid",
        "VIP": 0,
        "Ban": 0
    },
    {
        "ID": 62136,
        "UserID": "auth0|60c4ddb2612d820070a5e2f6",
        "IdentityID": 45010,
        "CreatedAt": "2022-09-25 05:14:53",
        "Flags": 0,
        "VerdictType": 0,
        "VerdictResult": 0,
        "VerdictName": "Valid",
        "VerdictValue": "Valid",
        "VIP": 0,
        "Ban": 0
    },
    {
        "ID": 62135,
        "UserID": "auth0|60c4ddb2612d820070a5e2f6",
        "IdentityID": 45009,
        "CreatedAt": "2022-09-25 05:14:45",
        "Flags": 0,
        "VerdictType": 0,
        "VerdictResult": 0,
        "VerdictName": "Valid",
        "VerdictValue": "Valid",
        "VIP": 0,
        "Ban": 0
    },
    {
        "ID": 62134,
        "UserID": "auth0|60c4ddb2612d820070a5e2f6",
        "IdentityID": 45008,
        "CreatedAt": "2022-09-25 05:14:36",
        "Flags": 0,
        "VerdictType": 0,
        "VerdictResult": 0,
        "VerdictName": "Valid",
        "VerdictValue": "Valid",
        "VIP": 0,
        "Ban": 0
    },
    {
        "ID": 62133,
        "UserID": "auth0|60c4ddb2612d820070a5e2f6",
        "IdentityID": 9361,
        "CreatedAt": "2022-09-25 05:14:28",
        "Flags": 0,
        "VerdictType": 0,
        "VerdictResult": 0,
        "VerdictName": "Valid",
        "VerdictValue": "Valid",
        "VIP": 0,
        "Ban": 0
    },
    {
        "ID": 62132,
        "UserID": "auth0|60c4ddb2612d820070a5e2f6",
        "IdentityID": 42371,
        "CreatedAt": "2022-09-25 05:14:19",
        "Flags": 0,
        "VerdictType": 0,
        "VerdictResult": 0,
        "VerdictName": "Valid",
        "VerdictValue": "Valid",
        "VIP": 0,
        "Ban": 0
    },
    {
        "ID": 62131,
        "UserID": "auth0|60c4ddb2612d820070a5e2f6",
        "IdentityID": 45007,
        "CreatedAt": "2022-09-25 05:14:07",
        "Flags": 0,
        "VerdictType": 0,
        "VerdictResult": 0,
        "VerdictName": "Valid",
        "VerdictValue": "Valid",
        "VIP": 0,
        "Ban": 0
    },
    {
        "ID": 62130,
        "UserID": "auth0|60c4ddb2612d820070a5e2f6",
        "IdentityID": 45006,
        "CreatedAt": "2022-09-25 05:13:58",
        "Flags": 0,
        "VerdictType": 0,
        "VerdictResult": 0,
        "VerdictName": "Valid",
        "VerdictValue": "Valid",
        "VIP": 0,
        "Ban": 0
    },
    {
        "ID": 62129,
        "UserID": "auth0|60c4ddb2612d820070a5e2f6",
        "IdentityID": 45005,
        "CreatedAt": "2022-09-25 05:13:52",
        "Flags": 0,
        "VerdictType": 0,
        "VerdictResult": 0,
        "VerdictName": "Valid",
        "VerdictValue": "Valid",
        "VIP": 0,
        "Ban": 0
    },
    {
        "ID": 62128,
        "UserID": "auth0|60c4ddb2612d820070a5e2f6",
        "IdentityID": 45004,
        "CreatedAt": "2022-09-25 05:13:38",
        "Flags": 0,
        "VerdictType": 0,
        "VerdictResult": 0,
        "VerdictName": "Valid",
        "VerdictValue": "Valid",
        "VIP": 0,
        "Ban": 0
    },
    {
        "ID": 62127,
        "UserID": "auth0|60c4ddb2612d820070a5e2f6",
        "IdentityID": 45003,
        "CreatedAt": "2022-09-25 05:13:29",
        "Flags": 0,
        "VerdictType": 0,
        "VerdictResult": 0,
        "VerdictName": "Valid",
        "VerdictValue": "Valid",
        "VIP": 0,
        "Ban": 0
    },
    {
        "ID": 62151,
        "UserID": "auth0|60c4ddb2612d820070a5e2f6",
        "IdentityID": 25895,
        "CreatedAt": "2022-09-25 05:23:56",
        "Flags": 0,
        "VerdictType": 0,
        "VerdictResult": 0,
        "VerdictName": "Valid",
        "VerdictValue": "Valid",
        "VIP": 0,
        "Ban": 0
    },
    {
        "ID": 62150,
        "UserID": "auth0|60c4ddb2612d820070a5e2f6",
        "IdentityID": 45020,
        "CreatedAt": "2022-09-25 05:23:49",
        "Flags": 0,
        "VerdictType": 0,
        "VerdictResult": 0,
        "VerdictName": "Valid",
        "VerdictValue": "Valid",
        "VIP": 0,
        "Ban": 0
    },
    {
        "ID": 62149,
        "UserID": "auth0|60c4ddb2612d820070a5e2f6",
        "IdentityID": 4769,
        "CreatedAt": "2022-09-25 05:23:28",
        "Flags": 0,
        "VerdictType": 0,
        "VerdictResult": 0,
        "VerdictName": "Valid",
        "VerdictValue": "Valid",
        "VIP": 0,
        "Ban": 0
    },
    {
        "ID": 62148,
        "UserID": "auth0|60c4ddb2612d820070a5e2f6",
        "IdentityID": 36099,
        "CreatedAt": "2022-09-25 05:22:25",
        "Flags": 0,
        "VerdictType": 0,
        "VerdictResult": 0,
        "VerdictName": "Valid",
        "VerdictValue": "Valid",
        "VIP": 0,
        "Ban": 0
    },
    {
        "ID": 62147,
        "UserID": "auth0|60c4ddb2612d820070a5e2f6",
        "IdentityID": 29129,
        "CreatedAt": "2022-09-25 05:22:12",
        "Flags": 0,
        "VerdictType": 0,
        "VerdictResult": 0,
        "VerdictName": "Valid",
        "VerdictValue": "Valid",
        "VIP": 0,
        "Ban": 0
    },
    {
        "ID": 62146,
        "UserID": "auth0|60c4ddb2612d820070a5e2f6",
        "IdentityID": 45019,
        "CreatedAt": "2022-09-25 05:18:21",
        "Flags": 0,
        "VerdictType": 0,
        "VerdictResult": 0,
        "VerdictName": "Valid",
        "VerdictValue": "Valid",
        "VIP": 0,
        "Ban": 0
    },
    {
        "ID": 62145,
        "UserID": "auth0|60c4ddb2612d820070a5e2f6",
        "IdentityID": 45018,
        "CreatedAt": "2022-09-25 05:17:59",
        "Flags": 0,
        "VerdictType": 0,
        "VerdictResult": 0,
        "VerdictName": "Valid",
        "VerdictValue": "Valid",
        "VIP": 0,
        "Ban": 0
    },
    {
        "ID": 62144,
        "UserID": "auth0|60c4ddb2612d820070a5e2f6",
        "IdentityID": 45017,
        "CreatedAt": "2022-09-25 05:17:48",
        "Flags": 0,
        "VerdictType": 0,
        "VerdictResult": 0,
        "VerdictName": "Valid",
        "VerdictValue": "Valid",
        "VIP": 0,
        "Ban": 0
    },
    {
        "ID": 62143,
        "UserID": "auth0|60c4ddb2612d820070a5e2f6",
        "IdentityID": 45016,
        "CreatedAt": "2022-09-25 05:17:41",
        "Flags": 0,
        "VerdictType": 0,
        "VerdictResult": 0,
        "VerdictName": "Valid",
        "VerdictValue": "Valid",
        "VIP": 0,
        "Ban": 0
    },
    {
        "ID": 62142,
        "UserID": "auth0|60c4ddb2612d820070a5e2f6",
        "IdentityID": 45015,
        "CreatedAt": "2022-09-25 05:17:28",
        "Flags": 0,
        "VerdictType": 0,
        "VerdictResult": 0,
        "VerdictName": "Valid",
        "VerdictValue": "Valid",
        "VIP": 0,
        "Ban": 0
    },
    {
        "ID": 62141,
        "UserID": "auth0|60c4ddb2612d820070a5e2f6",
        "IdentityID": 45014,
        "CreatedAt": "2022-09-25 05:17:16",
        "Flags": 0,
        "VerdictType": 0,
        "VerdictResult": 0,
        "VerdictName": "Valid",
        "VerdictValue": "Valid",
        "VIP": 0,
        "Ban": 0
    },
    {
        "ID": 62140,
        "UserID": "auth0|60c4ddb2612d820070a5e2f6",
        "IdentityID": 44325,
        "CreatedAt": "2022-09-25 05:16:17",
        "Flags": 0,
        "VerdictType": 0,
        "VerdictResult": 0,
        "VerdictName": "Valid",
        "VerdictValue": "Valid",
        "VIP": 0,
        "Ban": 0
    },
    {
        "ID": 62139,
        "UserID": "auth0|60c4ddb2612d820070a5e2f6",
        "IdentityID": 45013,
        "CreatedAt": "2022-09-25 05:15:17",
        "Flags": 0,
        "VerdictType": 0,
        "VerdictResult": 0,
        "VerdictName": "Valid",
        "VerdictValue": "Valid",
        "VIP": 0,
        "Ban": 0
    },
    {
        "ID": 62138,
        "UserID": "auth0|60c4ddb2612d820070a5e2f6",
        "IdentityID": 45012,
        "CreatedAt": "2022-09-25 05:15:09",
        "Flags": 0,
        "VerdictType": 0,
        "VerdictResult": 0,
        "VerdictName": "Valid",
        "VerdictValue": "Valid",
        "VIP": 0,
        "Ban": 0
    },
    {
        "ID": 62137,
        "UserID": "auth0|60c4ddb2612d820070a5e2f6",
        "IdentityID": 45011,
        "CreatedAt": "2022-09-25 05:15:01",
        "Flags": 0,
        "VerdictType": 0,
        "VerdictResult": 0,
        "VerdictName": "Valid",
        "VerdictValue": "Valid",
        "VIP": 0,
        "Ban": 0
    },
    {
        "ID": 62136,
        "UserID": "auth0|60c4ddb2612d820070a5e2f6",
        "IdentityID": 45010,
        "CreatedAt": "2022-09-25 05:14:53",
        "Flags": 0,
        "VerdictType": 0,
        "VerdictResult": 0,
        "VerdictName": "Valid",
        "VerdictValue": "Valid",
        "VIP": 0,
        "Ban": 0
    },
    {
        "ID": 62135,
        "UserID": "auth0|60c4ddb2612d820070a5e2f6",
        "IdentityID": 45009,
        "CreatedAt": "2022-09-25 05:14:45",
        "Flags": 0,
        "VerdictType": 0,
        "VerdictResult": 0,
        "VerdictName": "Valid",
        "VerdictValue": "Valid",
        "VIP": 0,
        "Ban": 0
    },
    {
        "ID": 62134,
        "UserID": "auth0|60c4ddb2612d820070a5e2f6",
        "IdentityID": 45008,
        "CreatedAt": "2022-09-25 05:14:36",
        "Flags": 0,
        "VerdictType": 0,
        "VerdictResult": 0,
        "VerdictName": "Valid",
        "VerdictValue": "Valid",
        "VIP": 0,
        "Ban": 0
    },
    {
        "ID": 62133,
        "UserID": "auth0|60c4ddb2612d820070a5e2f6",
        "IdentityID": 9361,
        "CreatedAt": "2022-09-25 05:14:28",
        "Flags": 0,
        "VerdictType": 0,
        "VerdictResult": 0,
        "VerdictName": "Valid",
        "VerdictValue": "Valid",
        "VIP": 0,
        "Ban": 0
    },
    {
        "ID": 62132,
        "UserID": "auth0|60c4ddb2612d820070a5e2f6",
        "IdentityID": 42371,
        "CreatedAt": "2022-09-25 05:14:19",
        "Flags": 0,
        "VerdictType": 0,
        "VerdictResult": 0,
        "VerdictName": "Valid",
        "VerdictValue": "Valid",
        "VIP": 0,
        "Ban": 0
    },
    {
        "ID": 62131,
        "UserID": "auth0|60c4ddb2612d820070a5e2f6",
        "IdentityID": 45007,
        "CreatedAt": "2022-09-25 05:14:07",
        "Flags": 0,
        "VerdictType": 0,
        "VerdictResult": 0,
        "VerdictName": "Valid",
        "VerdictValue": "Valid",
        "VIP": 0,
        "Ban": 0
    },
    {
        "ID": 62130,
        "UserID": "auth0|60c4ddb2612d820070a5e2f6",
        "IdentityID": 45006,
        "CreatedAt": "2022-09-25 05:13:58",
        "Flags": 0,
        "VerdictType": 0,
        "VerdictResult": 0,
        "VerdictName": "Valid",
        "VerdictValue": "Valid",
        "VIP": 0,
        "Ban": 0
    },
    {
        "ID": 62129,
        "UserID": "auth0|60c4ddb2612d820070a5e2f6",
        "IdentityID": 45005,
        "CreatedAt": "2022-09-25 05:13:52",
        "Flags": 0,
        "VerdictType": 0,
        "VerdictResult": 0,
        "VerdictName": "Valid",
        "VerdictValue": "Valid",
        "VIP": 0,
        "Ban": 0
    },
    {
        "ID": 62128,
        "UserID": "auth0|60c4ddb2612d820070a5e2f6",
        "IdentityID": 45004,
        "CreatedAt": "2022-09-25 05:13:38",
        "Flags": 0,
        "VerdictType": 0,
        "VerdictResult": 0,
        "VerdictName": "Valid",
        "VerdictValue": "Valid",
        "VIP": 0,
        "Ban": 0
    },
    {
        "ID": 62127,
        "UserID": "auth0|60c4ddb2612d820070a5e2f6",
        "IdentityID": 45003,
        "CreatedAt": "2022-09-25 05:13:29",
        "Flags": 0,
        "VerdictType": 0,
        "VerdictResult": 0,
        "VerdictName": "Valid",
        "VerdictValue": "Valid",
        "VIP": 0,
        "Ban": 0
    },
    {
        "ID": 62151,
        "UserID": "auth0|60c4ddb2612d820070a5e2f6",
        "IdentityID": 25895,
        "CreatedAt": "2022-09-25 05:23:56",
        "Flags": 0,
        "VerdictType": 0,
        "VerdictResult": 0,
        "VerdictName": "Valid",
        "VerdictValue": "Valid",
        "VIP": 0,
        "Ban": 0
    },
    {
        "ID": 62150,
        "UserID": "auth0|60c4ddb2612d820070a5e2f6",
        "IdentityID": 45020,
        "CreatedAt": "2022-09-25 05:23:49",
        "Flags": 0,
        "VerdictType": 0,
        "VerdictResult": 0,
        "VerdictName": "Valid",
        "VerdictValue": "Valid",
        "VIP": 0,
        "Ban": 0
    },
    {
        "ID": 62149,
        "UserID": "auth0|60c4ddb2612d820070a5e2f6",
        "IdentityID": 4769,
        "CreatedAt": "2022-09-25 05:23:28",
        "Flags": 0,
        "VerdictType": 0,
        "VerdictResult": 0,
        "VerdictName": "Valid",
        "VerdictValue": "Valid",
        "VIP": 0,
        "Ban": 0
    },
    {
        "ID": 62148,
        "UserID": "auth0|60c4ddb2612d820070a5e2f6",
        "IdentityID": 36099,
        "CreatedAt": "2022-09-25 05:22:25",
        "Flags": 0,
        "VerdictType": 0,
        "VerdictResult": 0,
        "VerdictName": "Valid",
        "VerdictValue": "Valid",
        "VIP": 0,
        "Ban": 0
    },
    {
        "ID": 62147,
        "UserID": "auth0|60c4ddb2612d820070a5e2f6",
        "IdentityID": 29129,
        "CreatedAt": "2022-09-25 05:22:12",
        "Flags": 0,
        "VerdictType": 0,
        "VerdictResult": 0,
        "VerdictName": "Valid",
        "VerdictValue": "Valid",
        "VIP": 0,
        "Ban": 0
    },
    {
        "ID": 62146,
        "UserID": "auth0|60c4ddb2612d820070a5e2f6",
        "IdentityID": 45019,
        "CreatedAt": "2022-09-25 05:18:21",
        "Flags": 0,
        "VerdictType": 0,
        "VerdictResult": 0,
        "VerdictName": "Valid",
        "VerdictValue": "Valid",
        "VIP": 0,
        "Ban": 0
    },
    {
        "ID": 62145,
        "UserID": "auth0|60c4ddb2612d820070a5e2f6",
        "IdentityID": 45018,
        "CreatedAt": "2022-09-25 05:17:59",
        "Flags": 0,
        "VerdictType": 0,
        "VerdictResult": 0,
        "VerdictName": "Valid",
        "VerdictValue": "Valid",
        "VIP": 0,
        "Ban": 0
    },
    {
        "ID": 62144,
        "UserID": "auth0|60c4ddb2612d820070a5e2f6",
        "IdentityID": 45017,
        "CreatedAt": "2022-09-25 05:17:48",
        "Flags": 0,
        "VerdictType": 0,
        "VerdictResult": 0,
        "VerdictName": "Valid",
        "VerdictValue": "Valid",
        "VIP": 0,
        "Ban": 0
    },
    {
        "ID": 62143,
        "UserID": "auth0|60c4ddb2612d820070a5e2f6",
        "IdentityID": 45016,
        "CreatedAt": "2022-09-25 05:17:41",
        "Flags": 0,
        "VerdictType": 0,
        "VerdictResult": 0,
        "VerdictName": "Valid",
        "VerdictValue": "Valid",
        "VIP": 0,
        "Ban": 0
    },
    {
        "ID": 62142,
        "UserID": "auth0|60c4ddb2612d820070a5e2f6",
        "IdentityID": 45015,
        "CreatedAt": "2022-09-25 05:17:28",
        "Flags": 0,
        "VerdictType": 0,
        "VerdictResult": 0,
        "VerdictName": "Valid",
        "VerdictValue": "Valid",
        "VIP": 0,
        "Ban": 0
    },
    {
        "ID": 62141,
        "UserID": "auth0|60c4ddb2612d820070a5e2f6",
        "IdentityID": 45014,
        "CreatedAt": "2022-09-25 05:17:16",
        "Flags": 0,
        "VerdictType": 0,
        "VerdictResult": 0,
        "VerdictName": "Valid",
        "VerdictValue": "Valid",
        "VIP": 0,
        "Ban": 0
    },
    {
        "ID": 62140,
        "UserID": "auth0|60c4ddb2612d820070a5e2f6",
        "IdentityID": 44325,
        "CreatedAt": "2022-09-25 05:16:17",
        "Flags": 0,
        "VerdictType": 0,
        "VerdictResult": 0,
        "VerdictName": "Valid",
        "VerdictValue": "Valid",
        "VIP": 0,
        "Ban": 0
    },
    {
        "ID": 62139,
        "UserID": "auth0|60c4ddb2612d820070a5e2f6",
        "IdentityID": 45013,
        "CreatedAt": "2022-09-25 05:15:17",
        "Flags": 0,
        "VerdictType": 0,
        "VerdictResult": 0,
        "VerdictName": "Valid",
        "VerdictValue": "Valid",
        "VIP": 0,
        "Ban": 0
    },
    {
        "ID": 62138,
        "UserID": "auth0|60c4ddb2612d820070a5e2f6",
        "IdentityID": 45012,
        "CreatedAt": "2022-09-25 05:15:09",
        "Flags": 0,
        "VerdictType": 0,
        "VerdictResult": 0,
        "VerdictName": "Valid",
        "VerdictValue": "Valid",
        "VIP": 0,
        "Ban": 0
    },
    {
        "ID": 62137,
        "UserID": "auth0|60c4ddb2612d820070a5e2f6",
        "IdentityID": 45011,
        "CreatedAt": "2022-09-25 05:15:01",
        "Flags": 0,
        "VerdictType": 0,
        "VerdictResult": 0,
        "VerdictName": "Valid",
        "VerdictValue": "Valid",
        "VIP": 0,
        "Ban": 0
    },
    {
        "ID": 62136,
        "UserID": "auth0|60c4ddb2612d820070a5e2f6",
        "IdentityID": 45010,
        "CreatedAt": "2022-09-25 05:14:53",
        "Flags": 0,
        "VerdictType": 0,
        "VerdictResult": 0,
        "VerdictName": "Valid",
        "VerdictValue": "Valid",
        "VIP": 0,
        "Ban": 0
    },
    {
        "ID": 62135,
        "UserID": "auth0|60c4ddb2612d820070a5e2f6",
        "IdentityID": 45009,
        "CreatedAt": "2022-09-25 05:14:45",
        "Flags": 0,
        "VerdictType": 0,
        "VerdictResult": 0,
        "VerdictName": "Valid",
        "VerdictValue": "Valid",
        "VIP": 0,
        "Ban": 0
    },
    {
        "ID": 62134,
        "UserID": "auth0|60c4ddb2612d820070a5e2f6",
        "IdentityID": 45008,
        "CreatedAt": "2022-09-25 05:14:36",
        "Flags": 0,
        "VerdictType": 0,
        "VerdictResult": 0,
        "VerdictName": "Valid",
        "VerdictValue": "Valid",
        "VIP": 0,
        "Ban": 0
    },
    {
        "ID": 62133,
        "UserID": "auth0|60c4ddb2612d820070a5e2f6",
        "IdentityID": 9361,
        "CreatedAt": "2022-09-25 05:14:28",
        "Flags": 0,
        "VerdictType": 0,
        "VerdictResult": 0,
        "VerdictName": "Valid",
        "VerdictValue": "Valid",
        "VIP": 0,
        "Ban": 0
    },
    {
        "ID": 62132,
        "UserID": "auth0|60c4ddb2612d820070a5e2f6",
        "IdentityID": 42371,
        "CreatedAt": "2022-09-25 05:14:19",
        "Flags": 0,
        "VerdictType": 0,
        "VerdictResult": 0,
        "VerdictName": "Valid",
        "VerdictValue": "Valid",
        "VIP": 0,
        "Ban": 0
    },
    {
        "ID": 62131,
        "UserID": "auth0|60c4ddb2612d820070a5e2f6",
        "IdentityID": 45007,
        "CreatedAt": "2022-09-25 05:14:07",
        "Flags": 0,
        "VerdictType": 0,
        "VerdictResult": 0,
        "VerdictName": "Valid",
        "VerdictValue": "Valid",
        "VIP": 0,
        "Ban": 0
    },
    {
        "ID": 62130,
        "UserID": "auth0|60c4ddb2612d820070a5e2f6",
        "IdentityID": 45006,
        "CreatedAt": "2022-09-25 05:13:58",
        "Flags": 0,
        "VerdictType": 0,
        "VerdictResult": 0,
        "VerdictName": "Valid",
        "VerdictValue": "Valid",
        "VIP": 0,
        "Ban": 0
    },
    {
        "ID": 62129,
        "UserID": "auth0|60c4ddb2612d820070a5e2f6",
        "IdentityID": 45005,
        "CreatedAt": "2022-09-25 05:13:52",
        "Flags": 0,
        "VerdictType": 0,
        "VerdictResult": 0,
        "VerdictName": "Valid",
        "VerdictValue": "Valid",
        "VIP": 0,
        "Ban": 0
    },
    {
        "ID": 62128,
        "UserID": "auth0|60c4ddb2612d820070a5e2f6",
        "IdentityID": 45004,
        "CreatedAt": "2022-09-25 05:13:38",
        "Flags": 0,
        "VerdictType": 0,
        "VerdictResult": 0,
        "VerdictName": "Valid",
        "VerdictValue": "Valid",
        "VIP": 0,
        "Ban": 0
    },
    {
        "ID": 62127,
        "UserID": "auth0|60c4ddb2612d820070a5e2f6",
        "IdentityID": 45003,
        "CreatedAt": "2022-09-25 05:13:29",
        "Flags": 0,
        "VerdictType": 0,
        "VerdictResult": 0,
        "VerdictName": "Valid",
        "VerdictValue": "Valid",
        "VIP": 0,
        "Ban": 0
    },
    {
        "ID": 62151,
        "UserID": "auth0|60c4ddb2612d820070a5e2f6",
        "IdentityID": 25895,
        "CreatedAt": "2022-09-25 05:23:56",
        "Flags": 0,
        "VerdictType": 0,
        "VerdictResult": 0,
        "VerdictName": "Valid",
        "VerdictValue": "Valid",
        "VIP": 0,
        "Ban": 0
    },
    {
        "ID": 62150,
        "UserID": "auth0|60c4ddb2612d820070a5e2f6",
        "IdentityID": 45020,
        "CreatedAt": "2022-09-25 05:23:49",
        "Flags": 0,
        "VerdictType": 0,
        "VerdictResult": 0,
        "VerdictName": "Valid",
        "VerdictValue": "Valid",
        "VIP": 0,
        "Ban": 0
    },
    {
        "ID": 62149,
        "UserID": "auth0|60c4ddb2612d820070a5e2f6",
        "IdentityID": 4769,
        "CreatedAt": "2022-09-25 05:23:28",
        "Flags": 0,
        "VerdictType": 0,
        "VerdictResult": 0,
        "VerdictName": "Valid",
        "VerdictValue": "Valid",
        "VIP": 0,
        "Ban": 0
    },
    {
        "ID": 62148,
        "UserID": "auth0|60c4ddb2612d820070a5e2f6",
        "IdentityID": 36099,
        "CreatedAt": "2022-09-25 05:22:25",
        "Flags": 0,
        "VerdictType": 0,
        "VerdictResult": 0,
        "VerdictName": "Valid",
        "VerdictValue": "Valid",
        "VIP": 0,
        "Ban": 0
    },
    {
        "ID": 62147,
        "UserID": "auth0|60c4ddb2612d820070a5e2f6",
        "IdentityID": 29129,
        "CreatedAt": "2022-09-25 05:22:12",
        "Flags": 0,
        "VerdictType": 0,
        "VerdictResult": 0,
        "VerdictName": "Valid",
        "VerdictValue": "Valid",
        "VIP": 0,
        "Ban": 0
    },
    {
        "ID": 62146,
        "UserID": "auth0|60c4ddb2612d820070a5e2f6",
        "IdentityID": 45019,
        "CreatedAt": "2022-09-25 05:18:21",
        "Flags": 0,
        "VerdictType": 0,
        "VerdictResult": 0,
        "VerdictName": "Valid",
        "VerdictValue": "Valid",
        "VIP": 0,
        "Ban": 0
    },
    {
        "ID": 62145,
        "UserID": "auth0|60c4ddb2612d820070a5e2f6",
        "IdentityID": 45018,
        "CreatedAt": "2022-09-25 05:17:59",
        "Flags": 0,
        "VerdictType": 0,
        "VerdictResult": 0,
        "VerdictName": "Valid",
        "VerdictValue": "Valid",
        "VIP": 0,
        "Ban": 0
    },
    {
        "ID": 62144,
        "UserID": "auth0|60c4ddb2612d820070a5e2f6",
        "IdentityID": 45017,
        "CreatedAt": "2022-09-25 05:17:48",
        "Flags": 0,
        "VerdictType": 0,
        "VerdictResult": 0,
        "VerdictName": "Valid",
        "VerdictValue": "Valid",
        "VIP": 0,
        "Ban": 0
    },
    {
        "ID": 62143,
        "UserID": "auth0|60c4ddb2612d820070a5e2f6",
        "IdentityID": 45016,
        "CreatedAt": "2022-09-25 05:17:41",
        "Flags": 0,
        "VerdictType": 0,
        "VerdictResult": 0,
        "VerdictName": "Valid",
        "VerdictValue": "Valid",
        "VIP": 0,
        "Ban": 0
    },
    {
        "ID": 62142,
        "UserID": "auth0|60c4ddb2612d820070a5e2f6",
        "IdentityID": 45015,
        "CreatedAt": "2022-09-25 05:17:28",
        "Flags": 0,
        "VerdictType": 0,
        "VerdictResult": 0,
        "VerdictName": "Valid",
        "VerdictValue": "Valid",
        "VIP": 0,
        "Ban": 0
    },
    {
        "ID": 62141,
        "UserID": "auth0|60c4ddb2612d820070a5e2f6",
        "IdentityID": 45014,
        "CreatedAt": "2022-09-25 05:17:16",
        "Flags": 0,
        "VerdictType": 0,
        "VerdictResult": 0,
        "VerdictName": "Valid",
        "VerdictValue": "Valid",
        "VIP": 0,
        "Ban": 0
    },
    {
        "ID": 62140,
        "UserID": "auth0|60c4ddb2612d820070a5e2f6",
        "IdentityID": 44325,
        "CreatedAt": "2022-09-25 05:16:17",
        "Flags": 0,
        "VerdictType": 0,
        "VerdictResult": 0,
        "VerdictName": "Valid",
        "VerdictValue": "Valid",
        "VIP": 0,
        "Ban": 0
    },
    {
        "ID": 62139,
        "UserID": "auth0|60c4ddb2612d820070a5e2f6",
        "IdentityID": 45013,
        "CreatedAt": "2022-09-25 05:15:17",
        "Flags": 0,
        "VerdictType": 0,
        "VerdictResult": 0,
        "VerdictName": "Valid",
        "VerdictValue": "Valid",
        "VIP": 0,
        "Ban": 0
    },
    {
        "ID": 62138,
        "UserID": "auth0|60c4ddb2612d820070a5e2f6",
        "IdentityID": 45012,
        "CreatedAt": "2022-09-25 05:15:09",
        "Flags": 0,
        "VerdictType": 0,
        "VerdictResult": 0,
        "VerdictName": "Valid",
        "VerdictValue": "Valid",
        "VIP": 0,
        "Ban": 0
    },
    {
        "ID": 62137,
        "UserID": "auth0|60c4ddb2612d820070a5e2f6",
        "IdentityID": 45011,
        "CreatedAt": "2022-09-25 05:15:01",
        "Flags": 0,
        "VerdictType": 0,
        "VerdictResult": 0,
        "VerdictName": "Valid",
        "VerdictValue": "Valid",
        "VIP": 0,
        "Ban": 0
    },
    {
        "ID": 62136,
        "UserID": "auth0|60c4ddb2612d820070a5e2f6",
        "IdentityID": 45010,
        "CreatedAt": "2022-09-25 05:14:53",
        "Flags": 0,
        "VerdictType": 0,
        "VerdictResult": 0,
        "VerdictName": "Valid",
        "VerdictValue": "Valid",
        "VIP": 0,
        "Ban": 0
    },
    {
        "ID": 62135,
        "UserID": "auth0|60c4ddb2612d820070a5e2f6",
        "IdentityID": 45009,
        "CreatedAt": "2022-09-25 05:14:45",
        "Flags": 0,
        "VerdictType": 0,
        "VerdictResult": 0,
        "VerdictName": "Valid",
        "VerdictValue": "Valid",
        "VIP": 0,
        "Ban": 0
    },
    {
        "ID": 62134,
        "UserID": "auth0|60c4ddb2612d820070a5e2f6",
        "IdentityID": 45008,
        "CreatedAt": "2022-09-25 05:14:36",
        "Flags": 0,
        "VerdictType": 0,
        "VerdictResult": 0,
        "VerdictName": "Valid",
        "VerdictValue": "Valid",
        "VIP": 0,
        "Ban": 0
    },
    {
        "ID": 62133,
        "UserID": "auth0|60c4ddb2612d820070a5e2f6",
        "IdentityID": 9361,
        "CreatedAt": "2022-09-25 05:14:28",
        "Flags": 0,
        "VerdictType": 0,
        "VerdictResult": 0,
        "VerdictName": "Valid",
        "VerdictValue": "Valid",
        "VIP": 0,
        "Ban": 0
    },
    {
        "ID": 62132,
        "UserID": "auth0|60c4ddb2612d820070a5e2f6",
        "IdentityID": 42371,
        "CreatedAt": "2022-09-25 05:14:19",
        "Flags": 0,
        "VerdictType": 0,
        "VerdictResult": 0,
        "VerdictName": "Valid",
        "VerdictValue": "Valid",
        "VIP": 0,
        "Ban": 0
    },
    {
        "ID": 62131,
        "UserID": "auth0|60c4ddb2612d820070a5e2f6",
        "IdentityID": 45007,
        "CreatedAt": "2022-09-25 05:14:07",
        "Flags": 0,
        "VerdictType": 0,
        "VerdictResult": 0,
        "VerdictName": "Valid",
        "VerdictValue": "Valid",
        "VIP": 0,
        "Ban": 0
    },
    {
        "ID": 62130,
        "UserID": "auth0|60c4ddb2612d820070a5e2f6",
        "IdentityID": 45006,
        "CreatedAt": "2022-09-25 05:13:58",
        "Flags": 0,
        "VerdictType": 0,
        "VerdictResult": 0,
        "VerdictName": "Valid",
        "VerdictValue": "Valid",
        "VIP": 0,
        "Ban": 0
    },
    {
        "ID": 62129,
        "UserID": "auth0|60c4ddb2612d820070a5e2f6",
        "IdentityID": 45005,
        "CreatedAt": "2022-09-25 05:13:52",
        "Flags": 0,
        "VerdictType": 0,
        "VerdictResult": 0,
        "VerdictName": "Valid",
        "VerdictValue": "Valid",
        "VIP": 0,
        "Ban": 0
    },
    {
        "ID": 62128,
        "UserID": "auth0|60c4ddb2612d820070a5e2f6",
        "IdentityID": 45004,
        "CreatedAt": "2022-09-25 05:13:38",
        "Flags": 0,
        "VerdictType": 0,
        "VerdictResult": 0,
        "VerdictName": "Valid",
        "VerdictValue": "Valid",
        "VIP": 0,
        "Ban": 0
    },
    {
        "ID": 62127,
        "UserID": "auth0|60c4ddb2612d820070a5e2f6",
        "IdentityID": 45003,
        "CreatedAt": "2022-09-25 05:13:29",
        "Flags": 0,
        "VerdictType": 0,
        "VerdictResult": 0,
        "VerdictName": "Valid",
        "VerdictValue": "Valid",
        "VIP": 0,
        "Ban": 0
    },
    {
        "ID": 62151,
        "UserID": "auth0|60c4ddb2612d820070a5e2f6",
        "IdentityID": 25895,
        "CreatedAt": "2022-09-25 05:23:56",
        "Flags": 0,
        "VerdictType": 0,
        "VerdictResult": 0,
        "VerdictName": "Valid",
        "VerdictValue": "Valid",
        "VIP": 0,
        "Ban": 0
    },
    {
        "ID": 62150,
        "UserID": "auth0|60c4ddb2612d820070a5e2f6",
        "IdentityID": 45020,
        "CreatedAt": "2022-09-25 05:23:49",
        "Flags": 0,
        "VerdictType": 0,
        "VerdictResult": 0,
        "VerdictName": "Valid",
        "VerdictValue": "Valid",
        "VIP": 0,
        "Ban": 0
    },
    {
        "ID": 62149,
        "UserID": "auth0|60c4ddb2612d820070a5e2f6",
        "IdentityID": 4769,
        "CreatedAt": "2022-09-25 05:23:28",
        "Flags": 0,
        "VerdictType": 0,
        "VerdictResult": 0,
        "VerdictName": "Valid",
        "VerdictValue": "Valid",
        "VIP": 0,
        "Ban": 0
    },
    {
        "ID": 62148,
        "UserID": "auth0|60c4ddb2612d820070a5e2f6",
        "IdentityID": 36099,
        "CreatedAt": "2022-09-25 05:22:25",
        "Flags": 0,
        "VerdictType": 0,
        "VerdictResult": 0,
        "VerdictName": "Valid",
        "VerdictValue": "Valid",
        "VIP": 0,
        "Ban": 0
    },
    {
        "ID": 62147,
        "UserID": "auth0|60c4ddb2612d820070a5e2f6",
        "IdentityID": 29129,
        "CreatedAt": "2022-09-25 05:22:12",
        "Flags": 0,
        "VerdictType": 0,
        "VerdictResult": 0,
        "VerdictName": "Valid",
        "VerdictValue": "Valid",
        "VIP": 0,
        "Ban": 0
    },
    {
        "ID": 62146,
        "UserID": "auth0|60c4ddb2612d820070a5e2f6",
        "IdentityID": 45019,
        "CreatedAt": "2022-09-25 05:18:21",
        "Flags": 0,
        "VerdictType": 0,
        "VerdictResult": 0,
        "VerdictName": "Valid",
        "VerdictValue": "Valid",
        "VIP": 0,
        "Ban": 0
    },
    {
        "ID": 62145,
        "UserID": "auth0|60c4ddb2612d820070a5e2f6",
        "IdentityID": 45018,
        "CreatedAt": "2022-09-25 05:17:59",
        "Flags": 0,
        "VerdictType": 0,
        "VerdictResult": 0,
        "VerdictName": "Valid",
        "VerdictValue": "Valid",
        "VIP": 0,
        "Ban": 0
    },
    {
        "ID": 62144,
        "UserID": "auth0|60c4ddb2612d820070a5e2f6",
        "IdentityID": 45017,
        "CreatedAt": "2022-09-25 05:17:48",
        "Flags": 0,
        "VerdictType": 0,
        "VerdictResult": 0,
        "VerdictName": "Valid",
        "VerdictValue": "Valid",
        "VIP": 0,
        "Ban": 0
    },
    {
        "ID": 62143,
        "UserID": "auth0|60c4ddb2612d820070a5e2f6",
        "IdentityID": 45016,
        "CreatedAt": "2022-09-25 05:17:41",
        "Flags": 0,
        "VerdictType": 0,
        "VerdictResult": 0,
        "VerdictName": "Valid",
        "VerdictValue": "Valid",
        "VIP": 0,
        "Ban": 0
    },
    {
        "ID": 62142,
        "UserID": "auth0|60c4ddb2612d820070a5e2f6",
        "IdentityID": 45015,
        "CreatedAt": "2022-09-25 05:17:28",
        "Flags": 0,
        "VerdictType": 0,
        "VerdictResult": 0,
        "VerdictName": "Valid",
        "VerdictValue": "Valid",
        "VIP": 0,
        "Ban": 0
    },
    {
        "ID": 62141,
        "UserID": "auth0|60c4ddb2612d820070a5e2f6",
        "IdentityID": 45014,
        "CreatedAt": "2022-09-25 05:17:16",
        "Flags": 0,
        "VerdictType": 0,
        "VerdictResult": 0,
        "VerdictName": "Valid",
        "VerdictValue": "Valid",
        "VIP": 0,
        "Ban": 0
    },
    {
        "ID": 62140,
        "UserID": "auth0|60c4ddb2612d820070a5e2f6",
        "IdentityID": 44325,
        "CreatedAt": "2022-09-25 05:16:17",
        "Flags": 0,
        "VerdictType": 0,
        "VerdictResult": 0,
        "VerdictName": "Valid",
        "VerdictValue": "Valid",
        "VIP": 0,
        "Ban": 0
    },
    {
        "ID": 62139,
        "UserID": "auth0|60c4ddb2612d820070a5e2f6",
        "IdentityID": 45013,
        "CreatedAt": "2022-09-25 05:15:17",
        "Flags": 0,
        "VerdictType": 0,
        "VerdictResult": 0,
        "VerdictName": "Valid",
        "VerdictValue": "Valid",
        "VIP": 0,
        "Ban": 0
    },
    {
        "ID": 62138,
        "UserID": "auth0|60c4ddb2612d820070a5e2f6",
        "IdentityID": 45012,
        "CreatedAt": "2022-09-25 05:15:09",
        "Flags": 0,
        "VerdictType": 0,
        "VerdictResult": 0,
        "VerdictName": "Valid",
        "VerdictValue": "Valid",
        "VIP": 0,
        "Ban": 0
    },
    {
        "ID": 62137,
        "UserID": "auth0|60c4ddb2612d820070a5e2f6",
        "IdentityID": 45011,
        "CreatedAt": "2022-09-25 05:15:01",
        "Flags": 0,
        "VerdictType": 0,
        "VerdictResult": 0,
        "VerdictName": "Valid",
        "VerdictValue": "Valid",
        "VIP": 0,
        "Ban": 0
    },
    {
        "ID": 62136,
        "UserID": "auth0|60c4ddb2612d820070a5e2f6",
        "IdentityID": 45010,
        "CreatedAt": "2022-09-25 05:14:53",
        "Flags": 0,
        "VerdictType": 0,
        "VerdictResult": 0,
        "VerdictName": "Valid",
        "VerdictValue": "Valid",
        "VIP": 0,
        "Ban": 0
    },
    {
        "ID": 62135,
        "UserID": "auth0|60c4ddb2612d820070a5e2f6",
        "IdentityID": 45009,
        "CreatedAt": "2022-09-25 05:14:45",
        "Flags": 0,
        "VerdictType": 0,
        "VerdictResult": 0,
        "VerdictName": "Valid",
        "VerdictValue": "Valid",
        "VIP": 0,
        "Ban": 0
    },
    {
        "ID": 62134,
        "UserID": "auth0|60c4ddb2612d820070a5e2f6",
        "IdentityID": 45008,
        "CreatedAt": "2022-09-25 05:14:36",
        "Flags": 0,
        "VerdictType": 0,
        "VerdictResult": 0,
        "VerdictName": "Valid",
        "VerdictValue": "Valid",
        "VIP": 0,
        "Ban": 0
    },
    {
        "ID": 62133,
        "UserID": "auth0|60c4ddb2612d820070a5e2f6",
        "IdentityID": 9361,
        "CreatedAt": "2022-09-25 05:14:28",
        "Flags": 0,
        "VerdictType": 0,
        "VerdictResult": 0,
        "VerdictName": "Valid",
        "VerdictValue": "Valid",
        "VIP": 0,
        "Ban": 0
    },
    {
        "ID": 62132,
        "UserID": "auth0|60c4ddb2612d820070a5e2f6",
        "IdentityID": 42371,
        "CreatedAt": "2022-09-25 05:14:19",
        "Flags": 0,
        "VerdictType": 0,
        "VerdictResult": 0,
        "VerdictName": "Valid",
        "VerdictValue": "Valid",
        "VIP": 0,
        "Ban": 0
    },
    {
        "ID": 62131,
        "UserID": "auth0|60c4ddb2612d820070a5e2f6",
        "IdentityID": 45007,
        "CreatedAt": "2022-09-25 05:14:07",
        "Flags": 0,
        "VerdictType": 0,
        "VerdictResult": 0,
        "VerdictName": "Valid",
        "VerdictValue": "Valid",
        "VIP": 0,
        "Ban": 0
    },
    {
        "ID": 62130,
        "UserID": "auth0|60c4ddb2612d820070a5e2f6",
        "IdentityID": 45006,
        "CreatedAt": "2022-09-25 05:13:58",
        "Flags": 0,
        "VerdictType": 0,
        "VerdictResult": 0,
        "VerdictName": "Valid",
        "VerdictValue": "Valid",
        "VIP": 0,
        "Ban": 0
    },
    {
        "ID": 62129,
        "UserID": "auth0|60c4ddb2612d820070a5e2f6",
        "IdentityID": 45005,
        "CreatedAt": "2022-09-25 05:13:52",
        "Flags": 0,
        "VerdictType": 0,
        "VerdictResult": 0,
        "VerdictName": "Valid",
        "VerdictValue": "Valid",
        "VIP": 0,
        "Ban": 0
    },
    {
        "ID": 62128,
        "UserID": "auth0|60c4ddb2612d820070a5e2f6",
        "IdentityID": 45004,
        "CreatedAt": "2022-09-25 05:13:38",
        "Flags": 0,
        "VerdictType": 0,
        "VerdictResult": 0,
        "VerdictName": "Valid",
        "VerdictValue": "Valid",
        "VIP": 0,
        "Ban": 0
    },
    {
        "ID": 62127,
        "UserID": "auth0|60c4ddb2612d820070a5e2f6",
        "IdentityID": 45003,
        "CreatedAt": "2022-09-25 05:13:29",
        "Flags": 0,
        "VerdictType": 0,
        "VerdictResult": 0,
        "VerdictName": "Valid",
        "VerdictValue": "Valid",
        "VIP": 0,
        "Ban": 0
    },
    {
        "ID": 62151,
        "UserID": "auth0|60c4ddb2612d820070a5e2f6",
        "IdentityID": 25895,
        "CreatedAt": "2022-09-25 05:23:56",
        "Flags": 0,
        "VerdictType": 0,
        "VerdictResult": 0,
        "VerdictName": "Valid",
        "VerdictValue": "Valid",
        "VIP": 0,
        "Ban": 0
    },
    {
        "ID": 62150,
        "UserID": "auth0|60c4ddb2612d820070a5e2f6",
        "IdentityID": 45020,
        "CreatedAt": "2022-09-25 05:23:49",
        "Flags": 0,
        "VerdictType": 0,
        "VerdictResult": 0,
        "VerdictName": "Valid",
        "VerdictValue": "Valid",
        "VIP": 0,
        "Ban": 0
    },
    {
        "ID": 62149,
        "UserID": "auth0|60c4ddb2612d820070a5e2f6",
        "IdentityID": 4769,
        "CreatedAt": "2022-09-25 05:23:28",
        "Flags": 0,
        "VerdictType": 0,
        "VerdictResult": 0,
        "VerdictName": "Valid",
        "VerdictValue": "Valid",
        "VIP": 0,
        "Ban": 0
    },
    {
        "ID": 62148,
        "UserID": "auth0|60c4ddb2612d820070a5e2f6",
        "IdentityID": 36099,
        "CreatedAt": "2022-09-25 05:22:25",
        "Flags": 0,
        "VerdictType": 0,
        "VerdictResult": 0,
        "VerdictName": "Valid",
        "VerdictValue": "Valid",
        "VIP": 0,
        "Ban": 0
    },
    {
        "ID": 62147,
        "UserID": "auth0|60c4ddb2612d820070a5e2f6",
        "IdentityID": 29129,
        "CreatedAt": "2022-09-25 05:22:12",
        "Flags": 0,
        "VerdictType": 0,
        "VerdictResult": 0,
        "VerdictName": "Valid",
        "VerdictValue": "Valid",
        "VIP": 0,
        "Ban": 0
    },
    {
        "ID": 62146,
        "UserID": "auth0|60c4ddb2612d820070a5e2f6",
        "IdentityID": 45019,
        "CreatedAt": "2022-09-25 05:18:21",
        "Flags": 0,
        "VerdictType": 0,
        "VerdictResult": 0,
        "VerdictName": "Valid",
        "VerdictValue": "Valid",
        "VIP": 0,
        "Ban": 0
    },
    {
        "ID": 62145,
        "UserID": "auth0|60c4ddb2612d820070a5e2f6",
        "IdentityID": 45018,
        "CreatedAt": "2022-09-25 05:17:59",
        "Flags": 0,
        "VerdictType": 0,
        "VerdictResult": 0,
        "VerdictName": "Valid",
        "VerdictValue": "Valid",
        "VIP": 0,
        "Ban": 0
    },
    {
        "ID": 62144,
        "UserID": "auth0|60c4ddb2612d820070a5e2f6",
        "IdentityID": 45017,
        "CreatedAt": "2022-09-25 05:17:48",
        "Flags": 0,
        "VerdictType": 0,
        "VerdictResult": 0,
        "VerdictName": "Valid",
        "VerdictValue": "Valid",
        "VIP": 0,
        "Ban": 0
    },
    {
        "ID": 62143,
        "UserID": "auth0|60c4ddb2612d820070a5e2f6",
        "IdentityID": 45016,
        "CreatedAt": "2022-09-25 05:17:41",
        "Flags": 0,
        "VerdictType": 0,
        "VerdictResult": 0,
        "VerdictName": "Valid",
        "VerdictValue": "Valid",
        "VIP": 0,
        "Ban": 0
    },
    {
        "ID": 62142,
        "UserID": "auth0|60c4ddb2612d820070a5e2f6",
        "IdentityID": 45015,
        "CreatedAt": "2022-09-25 05:17:28",
        "Flags": 0,
        "VerdictType": 0,
        "VerdictResult": 0,
        "VerdictName": "Valid",
        "VerdictValue": "Valid",
        "VIP": 0,
        "Ban": 0
    },
    {
        "ID": 62141,
        "UserID": "auth0|60c4ddb2612d820070a5e2f6",
        "IdentityID": 45014,
        "CreatedAt": "2022-09-25 05:17:16",
        "Flags": 0,
        "VerdictType": 0,
        "VerdictResult": 0,
        "VerdictName": "Valid",
        "VerdictValue": "Valid",
        "VIP": 0,
        "Ban": 0
    },
    {
        "ID": 62140,
        "UserID": "auth0|60c4ddb2612d820070a5e2f6",
        "IdentityID": 44325,
        "CreatedAt": "2022-09-25 05:16:17",
        "Flags": 0,
        "VerdictType": 0,
        "VerdictResult": 0,
        "VerdictName": "Valid",
        "VerdictValue": "Valid",
        "VIP": 0,
        "Ban": 0
    },
    {
        "ID": 62139,
        "UserID": "auth0|60c4ddb2612d820070a5e2f6",
        "IdentityID": 45013,
        "CreatedAt": "2022-09-25 05:15:17",
        "Flags": 0,
        "VerdictType": 0,
        "VerdictResult": 0,
        "VerdictName": "Valid",
        "VerdictValue": "Valid",
        "VIP": 0,
        "Ban": 0
    },
    {
        "ID": 62138,
        "UserID": "auth0|60c4ddb2612d820070a5e2f6",
        "IdentityID": 45012,
        "CreatedAt": "2022-09-25 05:15:09",
        "Flags": 0,
        "VerdictType": 0,
        "VerdictResult": 0,
        "VerdictName": "Valid",
        "VerdictValue": "Valid",
        "VIP": 0,
        "Ban": 0
    },
    {
        "ID": 62137,
        "UserID": "auth0|60c4ddb2612d820070a5e2f6",
        "IdentityID": 45011,
        "CreatedAt": "2022-09-25 05:15:01",
        "Flags": 0,
        "VerdictType": 0,
        "VerdictResult": 0,
        "VerdictName": "Valid",
        "VerdictValue": "Valid",
        "VIP": 0,
        "Ban": 0
    },
    {
        "ID": 62136,
        "UserID": "auth0|60c4ddb2612d820070a5e2f6",
        "IdentityID": 45010,
        "CreatedAt": "2022-09-25 05:14:53",
        "Flags": 0,
        "VerdictType": 0,
        "VerdictResult": 0,
        "VerdictName": "Valid",
        "VerdictValue": "Valid",
        "VIP": 0,
        "Ban": 0
    },
    {
        "ID": 62135,
        "UserID": "auth0|60c4ddb2612d820070a5e2f6",
        "IdentityID": 45009,
        "CreatedAt": "2022-09-25 05:14:45",
        "Flags": 0,
        "VerdictType": 0,
        "VerdictResult": 0,
        "VerdictName": "Valid",
        "VerdictValue": "Valid",
        "VIP": 0,
        "Ban": 0
    },
    {
        "ID": 62134,
        "UserID": "auth0|60c4ddb2612d820070a5e2f6",
        "IdentityID": 45008,
        "CreatedAt": "2022-09-25 05:14:36",
        "Flags": 0,
        "VerdictType": 0,
        "VerdictResult": 0,
        "VerdictName": "Valid",
        "VerdictValue": "Valid",
        "VIP": 0,
        "Ban": 0
    },
    {
        "ID": 62133,
        "UserID": "auth0|60c4ddb2612d820070a5e2f6",
        "IdentityID": 9361,
        "CreatedAt": "2022-09-25 05:14:28",
        "Flags": 0,
        "VerdictType": 0,
        "VerdictResult": 0,
        "VerdictName": "Valid",
        "VerdictValue": "Valid",
        "VIP": 0,
        "Ban": 0
    },
    {
        "ID": 62132,
        "UserID": "auth0|60c4ddb2612d820070a5e2f6",
        "IdentityID": 42371,
        "CreatedAt": "2022-09-25 05:14:19",
        "Flags": 0,
        "VerdictType": 0,
        "VerdictResult": 0,
        "VerdictName": "Valid",
        "VerdictValue": "Valid",
        "VIP": 0,
        "Ban": 0
    },
    {
        "ID": 62131,
        "UserID": "auth0|60c4ddb2612d820070a5e2f6",
        "IdentityID": 45007,
        "CreatedAt": "2022-09-25 05:14:07",
        "Flags": 0,
        "VerdictType": 0,
        "VerdictResult": 0,
        "VerdictName": "Valid",
        "VerdictValue": "Valid",
        "VIP": 0,
        "Ban": 0
    },
    {
        "ID": 62130,
        "UserID": "auth0|60c4ddb2612d820070a5e2f6",
        "IdentityID": 45006,
        "CreatedAt": "2022-09-25 05:13:58",
        "Flags": 0,
        "VerdictType": 0,
        "VerdictResult": 0,
        "VerdictName": "Valid",
        "VerdictValue": "Valid",
        "VIP": 0,
        "Ban": 0
    },
    {
        "ID": 62129,
        "UserID": "auth0|60c4ddb2612d820070a5e2f6",
        "IdentityID": 45005,
        "CreatedAt": "2022-09-25 05:13:52",
        "Flags": 0,
        "VerdictType": 0,
        "VerdictResult": 0,
        "VerdictName": "Valid",
        "VerdictValue": "Valid",
        "VIP": 0,
        "Ban": 0
    },
    {
        "ID": 62128,
        "UserID": "auth0|60c4ddb2612d820070a5e2f6",
        "IdentityID": 45004,
        "CreatedAt": "2022-09-25 05:13:38",
        "Flags": 0,
        "VerdictType": 0,
        "VerdictResult": 0,
        "VerdictName": "Valid",
        "VerdictValue": "Valid",
        "VIP": 0,
        "Ban": 0
    },
    {
        "ID": 62127,
        "UserID": "auth0|60c4ddb2612d820070a5e2f6",
        "IdentityID": 45003,
        "CreatedAt": "2022-09-25 05:13:29",
        "Flags": 0,
        "VerdictType": 0,
        "VerdictResult": 0,
        "VerdictName": "Valid",
        "VerdictValue": "Valid",
        "VIP": 0,
        "Ban": 0
    },
    {
        "ID": 62151,
        "UserID": "auth0|60c4ddb2612d820070a5e2f6",
        "IdentityID": 25895,
        "CreatedAt": "2022-09-25 05:23:56",
        "Flags": 0,
        "VerdictType": 0,
        "VerdictResult": 0,
        "VerdictName": "Valid",
        "VerdictValue": "Valid",
        "VIP": 0,
        "Ban": 0
    },
    {
        "ID": 62150,
        "UserID": "auth0|60c4ddb2612d820070a5e2f6",
        "IdentityID": 45020,
        "CreatedAt": "2022-09-25 05:23:49",
        "Flags": 0,
        "VerdictType": 0,
        "VerdictResult": 0,
        "VerdictName": "Valid",
        "VerdictValue": "Valid",
        "VIP": 0,
        "Ban": 0
    },
    {
        "ID": 62149,
        "UserID": "auth0|60c4ddb2612d820070a5e2f6",
        "IdentityID": 4769,
        "CreatedAt": "2022-09-25 05:23:28",
        "Flags": 0,
        "VerdictType": 0,
        "VerdictResult": 0,
        "VerdictName": "Valid",
        "VerdictValue": "Valid",
        "VIP": 0,
        "Ban": 0
    },
    {
        "ID": 62148,
        "UserID": "auth0|60c4ddb2612d820070a5e2f6",
        "IdentityID": 36099,
        "CreatedAt": "2022-09-25 05:22:25",
        "Flags": 0,
        "VerdictType": 0,
        "VerdictResult": 0,
        "VerdictName": "Valid",
        "VerdictValue": "Valid",
        "VIP": 0,
        "Ban": 0
    },
    {
        "ID": 62147,
        "UserID": "auth0|60c4ddb2612d820070a5e2f6",
        "IdentityID": 29129,
        "CreatedAt": "2022-09-25 05:22:12",
        "Flags": 0,
        "VerdictType": 0,
        "VerdictResult": 0,
        "VerdictName": "Valid",
        "VerdictValue": "Valid",
        "VIP": 0,
        "Ban": 0
    },
    {
        "ID": 62146,
        "UserID": "auth0|60c4ddb2612d820070a5e2f6",
        "IdentityID": 45019,
        "CreatedAt": "2022-09-25 05:18:21",
        "Flags": 0,
        "VerdictType": 0,
        "VerdictResult": 0,
        "VerdictName": "Valid",
        "VerdictValue": "Valid",
        "VIP": 0,
        "Ban": 0
    },
    {
        "ID": 62145,
        "UserID": "auth0|60c4ddb2612d820070a5e2f6",
        "IdentityID": 45018,
        "CreatedAt": "2022-09-25 05:17:59",
        "Flags": 0,
        "VerdictType": 0,
        "VerdictResult": 0,
        "VerdictName": "Valid",
        "VerdictValue": "Valid",
        "VIP": 0,
        "Ban": 0
    },
    {
        "ID": 62144,
        "UserID": "auth0|60c4ddb2612d820070a5e2f6",
        "IdentityID": 45017,
        "CreatedAt": "2022-09-25 05:17:48",
        "Flags": 0,
        "VerdictType": 0,
        "VerdictResult": 0,
        "VerdictName": "Valid",
        "VerdictValue": "Valid",
        "VIP": 0,
        "Ban": 0
    },
    {
        "ID": 62143,
        "UserID": "auth0|60c4ddb2612d820070a5e2f6",
        "IdentityID": 45016,
        "CreatedAt": "2022-09-25 05:17:41",
        "Flags": 0,
        "VerdictType": 0,
        "VerdictResult": 0,
        "VerdictName": "Valid",
        "VerdictValue": "Valid",
        "VIP": 0,
        "Ban": 0
    },
    {
        "ID": 62142,
        "UserID": "auth0|60c4ddb2612d820070a5e2f6",
        "IdentityID": 45015,
        "CreatedAt": "2022-09-25 05:17:28",
        "Flags": 0,
        "VerdictType": 0,
        "VerdictResult": 0,
        "VerdictName": "Valid",
        "VerdictValue": "Valid",
        "VIP": 0,
        "Ban": 0
    },
    {
        "ID": 62141,
        "UserID": "auth0|60c4ddb2612d820070a5e2f6",
        "IdentityID": 45014,
        "CreatedAt": "2022-09-25 05:17:16",
        "Flags": 0,
        "VerdictType": 0,
        "VerdictResult": 0,
        "VerdictName": "Valid",
        "VerdictValue": "Valid",
        "VIP": 0,
        "Ban": 0
    },
    {
        "ID": 62140,
        "UserID": "auth0|60c4ddb2612d820070a5e2f6",
        "IdentityID": 44325,
        "CreatedAt": "2022-09-25 05:16:17",
        "Flags": 0,
        "VerdictType": 0,
        "VerdictResult": 0,
        "VerdictName": "Valid",
        "VerdictValue": "Valid",
        "VIP": 0,
        "Ban": 0
    },
    {
        "ID": 62139,
        "UserID": "auth0|60c4ddb2612d820070a5e2f6",
        "IdentityID": 45013,
        "CreatedAt": "2022-09-25 05:15:17",
        "Flags": 0,
        "VerdictType": 0,
        "VerdictResult": 0,
        "VerdictName": "Valid",
        "VerdictValue": "Valid",
        "VIP": 0,
        "Ban": 0
    },
    {
        "ID": 62138,
        "UserID": "auth0|60c4ddb2612d820070a5e2f6",
        "IdentityID": 45012,
        "CreatedAt": "2022-09-25 05:15:09",
        "Flags": 0,
        "VerdictType": 0,
        "VerdictResult": 0,
        "VerdictName": "Valid",
        "VerdictValue": "Valid",
        "VIP": 0,
        "Ban": 0
    },
    {
        "ID": 62137,
        "UserID": "auth0|60c4ddb2612d820070a5e2f6",
        "IdentityID": 45011,
        "CreatedAt": "2022-09-25 05:15:01",
        "Flags": 0,
        "VerdictType": 0,
        "VerdictResult": 0,
        "VerdictName": "Valid",
        "VerdictValue": "Valid",
        "VIP": 0,
        "Ban": 0
    },
    {
        "ID": 62136,
        "UserID": "auth0|60c4ddb2612d820070a5e2f6",
        "IdentityID": 45010,
        "CreatedAt": "2022-09-25 05:14:53",
        "Flags": 0,
        "VerdictType": 0,
        "VerdictResult": 0,
        "VerdictName": "Valid",
        "VerdictValue": "Valid",
        "VIP": 0,
        "Ban": 0
    },
    {
        "ID": 62135,
        "UserID": "auth0|60c4ddb2612d820070a5e2f6",
        "IdentityID": 45009,
        "CreatedAt": "2022-09-25 05:14:45",
        "Flags": 0,
        "VerdictType": 0,
        "VerdictResult": 0,
        "VerdictName": "Valid",
        "VerdictValue": "Valid",
        "VIP": 0,
        "Ban": 0
    },
    {
        "ID": 62134,
        "UserID": "auth0|60c4ddb2612d820070a5e2f6",
        "IdentityID": 45008,
        "CreatedAt": "2022-09-25 05:14:36",
        "Flags": 0,
        "VerdictType": 0,
        "VerdictResult": 0,
        "VerdictName": "Valid",
        "VerdictValue": "Valid",
        "VIP": 0,
        "Ban": 0
    },
    {
        "ID": 62133,
        "UserID": "auth0|60c4ddb2612d820070a5e2f6",
        "IdentityID": 9361,
        "CreatedAt": "2022-09-25 05:14:28",
        "Flags": 0,
        "VerdictType": 0,
        "VerdictResult": 0,
        "VerdictName": "Valid",
        "VerdictValue": "Valid",
        "VIP": 0,
        "Ban": 0
    },
    {
        "ID": 62132,
        "UserID": "auth0|60c4ddb2612d820070a5e2f6",
        "IdentityID": 42371,
        "CreatedAt": "2022-09-25 05:14:19",
        "Flags": 0,
        "VerdictType": 0,
        "VerdictResult": 0,
        "VerdictName": "Valid",
        "VerdictValue": "Valid",
        "VIP": 0,
        "Ban": 0
    },
    {
        "ID": 62131,
        "UserID": "auth0|60c4ddb2612d820070a5e2f6",
        "IdentityID": 45007,
        "CreatedAt": "2022-09-25 05:14:07",
        "Flags": 0,
        "VerdictType": 0,
        "VerdictResult": 0,
        "VerdictName": "Valid",
        "VerdictValue": "Valid",
        "VIP": 0,
        "Ban": 0
    },
    {
        "ID": 62130,
        "UserID": "auth0|60c4ddb2612d820070a5e2f6",
        "IdentityID": 45006,
        "CreatedAt": "2022-09-25 05:13:58",
        "Flags": 0,
        "VerdictType": 0,
        "VerdictResult": 0,
        "VerdictName": "Valid",
        "VerdictValue": "Valid",
        "VIP": 0,
        "Ban": 0
    },
    {
        "ID": 62129,
        "UserID": "auth0|60c4ddb2612d820070a5e2f6",
        "IdentityID": 45005,
        "CreatedAt": "2022-09-25 05:13:52",
        "Flags": 0,
        "VerdictType": 0,
        "VerdictResult": 0,
        "VerdictName": "Valid",
        "VerdictValue": "Valid",
        "VIP": 0,
        "Ban": 0
    },
    {
        "ID": 62128,
        "UserID": "auth0|60c4ddb2612d820070a5e2f6",
        "IdentityID": 45004,
        "CreatedAt": "2022-09-25 05:13:38",
        "Flags": 0,
        "VerdictType": 0,
        "VerdictResult": 0,
        "VerdictName": "Valid",
        "VerdictValue": "Valid",
        "VIP": 0,
        "Ban": 0
    },
    {
        "ID": 62127,
        "UserID": "auth0|60c4ddb2612d820070a5e2f6",
        "IdentityID": 45003,
        "CreatedAt": "2022-09-25 05:13:29",
        "Flags": 0,
        "VerdictType": 0,
        "VerdictResult": 0,
        "VerdictName": "Valid",
        "VerdictValue": "Valid",
        "VIP": 0,
        "Ban": 0
    },
    {
        "ID": 62151,
        "UserID": "auth0|60c4ddb2612d820070a5e2f6",
        "IdentityID": 25895,
        "CreatedAt": "2022-09-25 05:23:56",
        "Flags": 0,
        "VerdictType": 0,
        "VerdictResult": 0,
        "VerdictName": "Valid",
        "VerdictValue": "Valid",
        "VIP": 0,
        "Ban": 0
    },
    {
        "ID": 62150,
        "UserID": "auth0|60c4ddb2612d820070a5e2f6",
        "IdentityID": 45020,
        "CreatedAt": "2022-09-25 05:23:49",
        "Flags": 0,
        "VerdictType": 0,
        "VerdictResult": 0,
        "VerdictName": "Valid",
        "VerdictValue": "Valid",
        "VIP": 0,
        "Ban": 0
    },
    {
        "ID": 62149,
        "UserID": "auth0|60c4ddb2612d820070a5e2f6",
        "IdentityID": 4769,
        "CreatedAt": "2022-09-25 05:23:28",
        "Flags": 0,
        "VerdictType": 0,
        "VerdictResult": 0,
        "VerdictName": "Valid",
        "VerdictValue": "Valid",
        "VIP": 0,
        "Ban": 0
    },
    {
        "ID": 62148,
        "UserID": "auth0|60c4ddb2612d820070a5e2f6",
        "IdentityID": 36099,
        "CreatedAt": "2022-09-25 05:22:25",
        "Flags": 0,
        "VerdictType": 0,
        "VerdictResult": 0,
        "VerdictName": "Valid",
        "VerdictValue": "Valid",
        "VIP": 0,
        "Ban": 0
    },
    {
        "ID": 62147,
        "UserID": "auth0|60c4ddb2612d820070a5e2f6",
        "IdentityID": 29129,
        "CreatedAt": "2022-09-25 05:22:12",
        "Flags": 0,
        "VerdictType": 0,
        "VerdictResult": 0,
        "VerdictName": "Valid",
        "VerdictValue": "Valid",
        "VIP": 0,
        "Ban": 0
    },
    {
        "ID": 62146,
        "UserID": "auth0|60c4ddb2612d820070a5e2f6",
        "IdentityID": 45019,
        "CreatedAt": "2022-09-25 05:18:21",
        "Flags": 0,
        "VerdictType": 0,
        "VerdictResult": 0,
        "VerdictName": "Valid",
        "VerdictValue": "Valid",
        "VIP": 0,
        "Ban": 0
    },
    {
        "ID": 62145,
        "UserID": "auth0|60c4ddb2612d820070a5e2f6",
        "IdentityID": 45018,
        "CreatedAt": "2022-09-25 05:17:59",
        "Flags": 0,
        "VerdictType": 0,
        "VerdictResult": 0,
        "VerdictName": "Valid",
        "VerdictValue": "Valid",
        "VIP": 0,
        "Ban": 0
    },
    {
        "ID": 62144,
        "UserID": "auth0|60c4ddb2612d820070a5e2f6",
        "IdentityID": 45017,
        "CreatedAt": "2022-09-25 05:17:48",
        "Flags": 0,
        "VerdictType": 0,
        "VerdictResult": 0,
        "VerdictName": "Valid",
        "VerdictValue": "Valid",
        "VIP": 0,
        "Ban": 0
    },
    {
        "ID": 62143,
        "UserID": "auth0|60c4ddb2612d820070a5e2f6",
        "IdentityID": 45016,
        "CreatedAt": "2022-09-25 05:17:41",
        "Flags": 0,
        "VerdictType": 0,
        "VerdictResult": 0,
        "VerdictName": "Valid",
        "VerdictValue": "Valid",
        "VIP": 0,
        "Ban": 0
    },
    {
        "ID": 62142,
        "UserID": "auth0|60c4ddb2612d820070a5e2f6",
        "IdentityID": 45015,
        "CreatedAt": "2022-09-25 05:17:28",
        "Flags": 0,
        "VerdictType": 0,
        "VerdictResult": 0,
        "VerdictName": "Valid",
        "VerdictValue": "Valid",
        "VIP": 0,
        "Ban": 0
    },
    {
        "ID": 62141,
        "UserID": "auth0|60c4ddb2612d820070a5e2f6",
        "IdentityID": 45014,
        "CreatedAt": "2022-09-25 05:17:16",
        "Flags": 0,
        "VerdictType": 0,
        "VerdictResult": 0,
        "VerdictName": "Valid",
        "VerdictValue": "Valid",
        "VIP": 0,
        "Ban": 0
    },
    {
        "ID": 62140,
        "UserID": "auth0|60c4ddb2612d820070a5e2f6",
        "IdentityID": 44325,
        "CreatedAt": "2022-09-25 05:16:17",
        "Flags": 0,
        "VerdictType": 0,
        "VerdictResult": 0,
        "VerdictName": "Valid",
        "VerdictValue": "Valid",
        "VIP": 0,
        "Ban": 0
    },
    {
        "ID": 62139,
        "UserID": "auth0|60c4ddb2612d820070a5e2f6",
        "IdentityID": 45013,
        "CreatedAt": "2022-09-25 05:15:17",
        "Flags": 0,
        "VerdictType": 0,
        "VerdictResult": 0,
        "VerdictName": "Valid",
        "VerdictValue": "Valid",
        "VIP": 0,
        "Ban": 0
    },
    {
        "ID": 62138,
        "UserID": "auth0|60c4ddb2612d820070a5e2f6",
        "IdentityID": 45012,
        "CreatedAt": "2022-09-25 05:15:09",
        "Flags": 0,
        "VerdictType": 0,
        "VerdictResult": 0,
        "VerdictName": "Valid",
        "VerdictValue": "Valid",
        "VIP": 0,
        "Ban": 0
    },
    {
        "ID": 62137,
        "UserID": "auth0|60c4ddb2612d820070a5e2f6",
        "IdentityID": 45011,
        "CreatedAt": "2022-09-25 05:15:01",
        "Flags": 0,
        "VerdictType": 0,
        "VerdictResult": 0,
        "VerdictName": "Valid",
        "VerdictValue": "Valid",
        "VIP": 0,
        "Ban": 0
    },
    {
        "ID": 62136,
        "UserID": "auth0|60c4ddb2612d820070a5e2f6",
        "IdentityID": 45010,
        "CreatedAt": "2022-09-25 05:14:53",
        "Flags": 0,
        "VerdictType": 0,
        "VerdictResult": 0,
        "VerdictName": "Valid",
        "VerdictValue": "Valid",
        "VIP": 0,
        "Ban": 0
    },
    {
        "ID": 62135,
        "UserID": "auth0|60c4ddb2612d820070a5e2f6",
        "IdentityID": 45009,
        "CreatedAt": "2022-09-25 05:14:45",
        "Flags": 0,
        "VerdictType": 0,
        "VerdictResult": 0,
        "VerdictName": "Valid",
        "VerdictValue": "Valid",
        "VIP": 0,
        "Ban": 0
    },
    {
        "ID": 62134,
        "UserID": "auth0|60c4ddb2612d820070a5e2f6",
        "IdentityID": 45008,
        "CreatedAt": "2022-09-25 05:14:36",
        "Flags": 0,
        "VerdictType": 0,
        "VerdictResult": 0,
        "VerdictName": "Valid",
        "VerdictValue": "Valid",
        "VIP": 0,
        "Ban": 0
    },
    {
        "ID": 62133,
        "UserID": "auth0|60c4ddb2612d820070a5e2f6",
        "IdentityID": 9361,
        "CreatedAt": "2022-09-25 05:14:28",
        "Flags": 0,
        "VerdictType": 0,
        "VerdictResult": 0,
        "VerdictName": "Valid",
        "VerdictValue": "Valid",
        "VIP": 0,
        "Ban": 0
    },
    {
        "ID": 62132,
        "UserID": "auth0|60c4ddb2612d820070a5e2f6",
        "IdentityID": 42371,
        "CreatedAt": "2022-09-25 05:14:19",
        "Flags": 0,
        "VerdictType": 0,
        "VerdictResult": 0,
        "VerdictName": "Valid",
        "VerdictValue": "Valid",
        "VIP": 0,
        "Ban": 0
    },
    {
        "ID": 62131,
        "UserID": "auth0|60c4ddb2612d820070a5e2f6",
        "IdentityID": 45007,
        "CreatedAt": "2022-09-25 05:14:07",
        "Flags": 0,
        "VerdictType": 0,
        "VerdictResult": 0,
        "VerdictName": "Valid",
        "VerdictValue": "Valid",
        "VIP": 0,
        "Ban": 0
    },
    {
        "ID": 62130,
        "UserID": "auth0|60c4ddb2612d820070a5e2f6",
        "IdentityID": 45006,
        "CreatedAt": "2022-09-25 05:13:58",
        "Flags": 0,
        "VerdictType": 0,
        "VerdictResult": 0,
        "VerdictName": "Valid",
        "VerdictValue": "Valid",
        "VIP": 0,
        "Ban": 0
    },
    {
        "ID": 62129,
        "UserID": "auth0|60c4ddb2612d820070a5e2f6",
        "IdentityID": 45005,
        "CreatedAt": "2022-09-25 05:13:52",
        "Flags": 0,
        "VerdictType": 0,
        "VerdictResult": 0,
        "VerdictName": "Valid",
        "VerdictValue": "Valid",
        "VIP": 0,
        "Ban": 0
    },
    {
        "ID": 62128,
        "UserID": "auth0|60c4ddb2612d820070a5e2f6",
        "IdentityID": 45004,
        "CreatedAt": "2022-09-25 05:13:38",
        "Flags": 0,
        "VerdictType": 0,
        "VerdictResult": 0,
        "VerdictName": "Valid",
        "VerdictValue": "Valid",
        "VIP": 0,
        "Ban": 0
    },
    {
        "ID": 62127,
        "UserID": "auth0|60c4ddb2612d820070a5e2f6",
        "IdentityID": 45003,
        "CreatedAt": "2022-09-25 05:13:29",
        "Flags": 0,
        "VerdictType": 0,
        "VerdictResult": 0,
        "VerdictName": "Valid",
        "VerdictValue": "Valid",
        "VIP": 0,
        "Ban": 0
    }
]